AUTHORS
meringue/__init__.py
meringue/api/__init__.py
meringue/api/apps.py
meringue/api/handlers.py
meringue/api/routers.py
meringue/api/utils.py
meringue/api/docs/__init__.py
meringue/api/docs/patchers.py
meringue/api/docs/views.py
meringue/conf/__init__.py
meringue/conf/default_settings.py
meringue/core/__init__.py
meringue/core/apps.py
meringue/core/db.py
meringue/core/models.py
meringue/core/options.py
meringue/core/query.py
meringue/core/translation.py
meringue/core/upload_handlers.py
meringue/core/views.py
meringue/core/locale/en/LC_MESSAGES/django.po
meringue/core/locale/ru/LC_MESSAGES/django.po
meringue/core/templatetags/__init__.py
meringue/core/templatetags/meringue_base.py
meringue/core/utils/__init__.py
meringue/core/utils/crypt.py
meringue/core/utils/datetime.py
meringue/core/utils/frontend.py
meringue/protected/__init__.py
meringue/protected/apps.py
meringue/protected/fields.py
meringue/protected/utils.py
meringue/protected/views.py
meringue/thumbnail/__init__.py
meringue/thumbnail/actions.py
meringue/thumbnail/apps.py
meringue/thumbnail/constants.py
meringue/thumbnail/drf_fields.py
meringue/thumbnail/exceptions.py
meringue/thumbnail/generators.py
meringue/thumbnail/images.py
meringue/thumbnail/properties.py
meringue/thumbnail/shortcuts.py
meringue/thumbnail/storage.py
meringue/thumbnail/types.py
meringue/thumbnail/templatetags/__init__.py
meringue/thumbnail/templatetags/m_thumbnails.py
meringue-1.3.3.dist-info/METADATA
meringue-1.3.3.dist-info/WHEEL
meringue-1.3.3.dist-info/licenses/AUTHORS
meringue-1.3.3.dist-info/licenses/LICENSE
meringue-1.3.3.dist-info/RECORD
