Metadata-Version: 2.4
Name: meringue
Version: 1.3.3
Summary: A set of various functionality for a Django based web application.
Project-URL: Documentation, https://dd.github.io/Meringue
Project-URL: Repository, https://github.com/dd/Meringue
Project-URL: Changelog, https://github.com/dd/Meringue/blob/master/CHANGELOG.md
Project-URL: Bug Tracker, https://github.com/dd/Meringue/issues
Author-email: Dmitry Dobrynin <dd@tovarisch.engineer>
License-Expression: MPL-2.0
License-File: AUTHORS
License-File: LICENSE
Keywords: django,utils
Classifier: Development Status :: 5 - Production/Stable
Classifier: Environment :: Plugins
Classifier: Environment :: Web Environment
Classifier: Framework :: Django
Classifier: Framework :: Django :: 2
Classifier: Framework :: Django :: 2.0
Classifier: Framework :: Django :: 2.1
Classifier: Framework :: Django :: 2.2
Classifier: Framework :: Django :: 3
Classifier: Framework :: Django :: 3.0
Classifier: Framework :: Django :: 3.1
Classifier: Framework :: Django :: 3.2
Classifier: Framework :: Django :: 4
Classifier: Framework :: Django :: 4.0
Classifier: Framework :: Django :: 4.1
Classifier: Framework :: Django :: 4.2
Classifier: Framework :: Django :: 5.0
Classifier: Intended Audience :: Developers
Classifier: License :: OSI Approved :: Mozilla Public License 2.0 (MPL 2.0)
Classifier: Natural Language :: English
Classifier: Operating System :: OS Independent
Classifier: Programming Language :: Python
Classifier: Programming Language :: Python :: 3
Classifier: Programming Language :: Python :: 3 :: Only
Classifier: Programming Language :: Python :: 3.10
Classifier: Programming Language :: Python :: 3.11
Classifier: Programming Language :: Python :: 3.12
Classifier: Programming Language :: Python :: Implementation :: CPython
Classifier: Programming Language :: Python :: Implementation :: PyPy
Classifier: Topic :: Internet :: WWW/HTTP
Classifier: Topic :: Internet :: WWW/HTTP :: Dynamic Content
Classifier: Topic :: Internet :: WWW/HTTP :: WSGI
Classifier: Topic :: Software Development :: Libraries
Requires-Python: >=3.10
Requires-Dist: django<6,>=2.0.0
Provides-Extra: cryptodome
Requires-Dist: pycryptodome==3.20.0; extra == 'cryptodome'
Provides-Extra: django-hosts
Requires-Dist: django-hosts<7,>=5.2; extra == 'django-hosts'
Provides-Extra: drf
Requires-Dist: djangorestframework<4,>=3.13; extra == 'drf'
Provides-Extra: drf-spectacular
Requires-Dist: drf-spectacular<1,>=0.26.3; extra == 'drf-spectacular'
Provides-Extra: modeltranslation
Requires-Dist: django-modeltranslation<0.20,>=0.17; extra == 'modeltranslation'
